odoo/addons/delivery_postlogistics_server_env/README.rst
odoo/addons/delivery_postlogistics_server_env/__init__.py
odoo/addons/delivery_postlogistics_server_env/__manifest__.py
odoo/addons/delivery_postlogistics_server_env/i18n/delivery_postlogistics_server_env.pot
odoo/addons/delivery_postlogistics_server_env/i18n/es.po
odoo/addons/delivery_postlogistics_server_env/i18n/it.po
odoo/addons/delivery_postlogistics_server_env/models/__init__.py
odoo/addons/delivery_postlogistics_server_env/models/delivery_carrier.py
odoo/addons/delivery_postlogistics_server_env/readme/CONTRIBUTORS.rst
odoo/addons/delivery_postlogistics_server_env/readme/CREDITS.rst
odoo/addons/delivery_postlogistics_server_env/readme/DESCRIPTION.rst
odoo/addons/delivery_postlogistics_server_env/static/description/icon.png
odoo/addons/delivery_postlogistics_server_env/static/description/index.html
odoo14_addon_delivery_postlogistics_server_env-14.0.1.0.1.dev9.dist-info/METADATA
odoo14_addon_delivery_postlogistics_server_env-14.0.1.0.1.dev9.dist-info/WHEEL
odoo14_addon_delivery_postlogistics_server_env-14.0.1.0.1.dev9.dist-info/top_level.txt
odoo14_addon_delivery_postlogistics_server_env-14.0.1.0.1.dev9.dist-info/RECORD
